vdfx/__init__.py
vdfx-1.0.0.dist-info/licenses/LICENSE
vdfx-1.0.0.dist-info/METADATA
vdfx-1.0.0.dist-info/WHEEL
vdfx-1.0.0.dist-info/top_level.txt
vdfx-1.0.0.dist-info/RECORD
