Metadata-Version: 2.4
Name: vdfx
Version: 1.0.0
Summary: Valve Data File for Python
License-Expression: MIT
Requires-Python: >=3.13.2
License-File: LICENSE
Requires-Dist: lark>=1.3.1
Dynamic: license-file
